yaml_walker/__init__.py
yaml_walker/__main__.py
yaml_walker/comparer.py
yaml_walker/get_error_info.py
yaml_walker/lookup.py
yaml_walker/query.py
yaml_walker/version.py
yaml_walker/yaml_dict.py
yaml_walker/api/__init__.py
yaml_walker/api/lookup.py
yaml_walker/api/query.py
yaml_walker/api/yaml_dict.py
yaml_walker/api/ypath.py
yaml_walker/tools/__init__.py
yaml_walker/tools/comparer.py
yaml_walker/tools/get_error_info.py
yaml_walker/unittests/__init__.py
yaml_walker/unittests/example.yaml
yaml_walker/unittests/test_ypath.py
yaml_walker-1.0.24.dist-info/LICENSE.txt
yaml_walker-1.0.24.dist-info/METADATA
yaml_walker-1.0.24.dist-info/WHEEL
yaml_walker-1.0.24.dist-info/top_level.txt
yaml_walker-1.0.24.dist-info/RECORD
