Metadata-Version: 2.1
Name: yaml-walker
Version: 1.0.24
Summary: Data walker (in dot notation style) & filter (Xpath analog) for yaml look data structure
Home-page: https://github.com/doguz2509/YamlWalker
Author: Dmitry Oguz
Author-email: doguz2509@gmail.com
License: MIT
Platform: UNKNOWN
Classifier: License :: OSI Approved :: MIT License
Classifier: Operating System :: OS Independent
Classifier: Programming Language :: Python :: 2.7
Classifier: Programming Language :: Python :: 3
Classifier: Programming Language :: Python :: 3.5
Classifier: Programming Language :: Python :: 3.6
Classifier: Programming Language :: Python :: 3.7
Classifier: Programming Language :: Python :: 3.8
Requires-Dist: PyYAML
